spotify_remote
