Metadata-Version: 1.0
Name: spotify-remote
Version: 0.1.1
Summary: A simple CLI to control the Spotify desktop client.
Home-page: UNKNOWN
Author: Christopher Rosell
Author-email: chrippa@tanuki.se
License: Simplified BSD
Platform: UNKNOWN
